VocaScribe/__init__.py
VocaScribe/vocascribe.py
VocaScribe-0.1.3.dist-info/LICENSE
VocaScribe-0.1.3.dist-info/METADATA
VocaScribe-0.1.3.dist-info/WHEEL
VocaScribe-0.1.3.dist-info/entry_points.txt
VocaScribe-0.1.3.dist-info/top_level.txt
VocaScribe-0.1.3.dist-info/RECORD
